Metadata-Version: 1.1
Name: changefinder
Version: 0.01
Summary: Online Change-Point Detection Library based on ChangeFinder Algorithm.
Home-page: https://bitbucket.org/aihara/changefinder/
Author: Shunsuke Aihara
Author-email: s.aihara gmail com
License: MIT License
Keywords: scipy,numpy,timeseries analysis
Platform: UNKNOWN
Classifier: Programming Language :: Python
Classifier: Topic :: Scientific/Engineering
